tread_contracts/__init__.py
tread_contracts/abi/Access.json
tread_contracts/abi/Attestations.json
tread_contracts/abi/IERC20.json
tread_contracts/attestations.py
tread_contracts/base_contract_client.py
tread_contracts/deployments.py
tread_contracts/util.py
tread_contracts-0.1.9.dist-info/METADATA
tread_contracts-0.1.9.dist-info/WHEEL
tread_contracts-0.1.9.dist-info/RECORD
