Metadata-Version: 2.3
Name: tread-contracts
Version: 0.1.9
Summary: 
Author: n-tread
Author-email: n-tread@users.noreply.github.com
Requires-Python: >=3.11,<4.0
Classifier: Programming Language :: Python :: 3
Classifier: Programming Language :: Python :: 3.11
Classifier: Programming Language :: Python :: 3.12
Classifier: Programming Language :: Python :: 3.13
Requires-Dist: eth-typing (>=5.0.0,<6.0.0)
Requires-Dist: requests (>=2.32.3,<3.0.0)
Requires-Dist: web3 (>=7.1.0,<8.0.0)
